DAY2/HIERARCHY_FULL_ADDER/GATE_LEVEL_MODEL/Hierarchy_full_adder.v
// Gate level modelling

// module half adder

module half_adder(input a, b, output sum, carry);

	xor(sum, a, b);
	and(carry, a, b);

endmodule

// combining 2 half adder + 1 or gate to make Full adder 

module hierarchy_full_adder(input a, b, c, output sum, carry);

wire sum1, carry1, carry2; // internal wires b/w 2 HF-adders

	// Instantiate two half adders
	
	half_adder hf1( .a(a), .b(b), .sum(sum1), .carry(carry1));

	half_adder hf2( .a(sum1), .b(c), .sum(sum), .carry(carry2));

	// final carry out

	or(carry, carry1, carry2);

endmodule

DAY2/HIERARCHY_FULL_ADDER/DATA_FLOW_MODEL/Hierarchy_full_adder_tb.v
// Hierarchy Full adder testbench

`timescale 1ns/1ps

module hierarchy_full_adder_tb;
wire sum, carry;
reg a, b, c;

	//instantiation
	hierarchy_full_adder uub(
	.sum(sum),
        .carry(carry),
	.a(a), 
	.b(b),
	.c(c));

	initial begin 
	
	$monitor("Time = %0t | a = %b | b = %b | c = %b | sum = %b | carry = %b", $time, a, b, c, sum, carry);
	$dumpfile("Hierarchy_full_adder_dump.vcd");
	$dumpvars;
	
	// combinations
	a = 0; b = 0; c = 0; #5
	a = 0; b = 0; c = 1; #5
	a = 0; b = 1; c = 0; #5
	a = 0; b = 1; c = 1; #5
	a = 1; b = 0; c = 0; #5
	a = 1; b = 0; c = 1; #5
	a = 1; b = 1; c = 0; #5
	a = 1; b = 1; c = 1; #5

	$finish; 
	end

endmodule

DAY2/HIERARCHY_FULL_ADDER/GATE_LEVEL_MODEL/Hierarchy_full_adder_dump.vcd
$date
	Sun Oct 12 18:13:10 2025
$end
$version
	Icarus Verilog
$end
$timescale
	1ps
$end
$scope module hierarchy_full_adder_tb $end
$var wire 1 ! sum $end
$var wire 1 " carry $end
$var reg 1 # a $end
$var reg 1 $ b $end
$var reg 1 % c $end
$scope module uub $end
$var wire 1 # a $end
$var wire 1 $ b $end
$var wire 1 % c $end
$var wire 1 " carry $end
$var wire 1 & sum1 $end
$var wire 1 ! sum $end
$var wire 1 ' carry2 $end
$var wire 1 ( carry1 $end
$scope module hf1 $end
$var wire 1 # a $end
$var wire 1 $ b $end
$var wire 1 ( carry $end
$var wire 1 & sum $end
$upscope $end
$scope module hf2 $end
$var wire 1 & a $end
$var wire 1 % b $end
$var wire 1 ' carry $end
$var wire 1 ! sum $end
$upscope $end
$upscope $end
$upscope $end
$enddefinitions $end
$comment Show the parameter values. $end
$dumpall
$end
#0
$dumpvars
0(
0'
0&
0%
0$
0#
0"
0!
$end
#5000
1!
1%
#10000
1&
0%
1$
#15000
1"
0!
1'
1%
#20000
0"
1!
0'
0%
0$
1#
#25000
1"
0!
1'
1%
#30000
0'
0&
1(
0%
1$
#35000
1!
1%
